LICENSE
MANIFEST.in
README.rst
requeriments.txt
setup.py
django_fbbot.egg-info/PKG-INFO
django_fbbot.egg-info/SOURCES.txt
django_fbbot.egg-info/dependency_links.txt
django_fbbot.egg-info/requires.txt
django_fbbot.egg-info/top_level.txt
djangobot/__init__.py
djangobot/settings.py
djangobot/urls.py
djangobot/wsgi.py
fbbot/__init__.py
fbbot/admin.py
fbbot/apps.py
fbbot/bot.py
fbbot/models.py
fbbot/tests.py
fbbot/urls.py
fbbot/views.py
fbbot/migrations/__init__.py
fbbot/static/fbbot/animal.mp4
fbbot/static/fbbot/books.png
fbbot/static/fbbot/falling_down.gif
fbbot/static/fbbot/python.png
fbbot/static/fbbot/sample.mp3
fbbot/static/fbbot/surprise_pkg.png
fbbot/static/fbbot/test.txt