Metadata-Version: 1.1
Name: django-fbbot
Version: 0.1
Summary: fbbot is a simple Django app to showcasing the Messenger Platform, make your facebook bot with Django
Home-page: https://github.com/espacioAntonio/Django-messenger-platform-bot
Author: espacioAntonio
Author-email: espacio.antonio@gmail.com
License: MIT License
Platform: UNKNOWN
Classifier: Environment :: Web Environment
Classifier: Framework :: Django
Classifier: Framework :: Django :: 1.11
Classifier: Intended Audience :: Developers
Classifier: License :: OSI Approved :: MIT License
Classifier: Operating System :: OS Independent
Classifier: Programming Language :: Python
Classifier: Programming Language :: Python :: 3
Classifier: Programming Language :: Python :: 3.4
Classifier: Programming Language :: Python :: 3.5
Classifier: Development Status :: 3 - Alpha
Classifier: Topic :: Communications :: Chat
Classifier: Topic :: Internet :: WWW/HTTP :: WSGI
